.gitignore
LICENSE.txt
MANIFEST.in
README.md
__test_dist.bat
__test_install_all.bat
__test_upload_pypi.bat
setup.py
lsx/__init__.py
lsx/__main__.py
lsx/auto.py
lsx/c.py
lsx/cls.py
lsx/dec.py
lsx/doc.py
lsx/gui.py
lsx/line.py
lsx/new.py
lsx/np.py
lsx/reg.py
lsx/util.py
lsx/version.py
lsx/windll.py
lsx.egg-info/PKG-INFO
lsx.egg-info/SOURCES.txt
lsx.egg-info/dependency_links.txt
lsx.egg-info/entry_points.txt
lsx.egg-info/top_level.txt
scripts/drag-open.reg
scripts/git-store-pswd.bat
scripts/pip-config.bat
scripts/repair-idle.bat
scripts/restart-explorer.bat
scripts/right-menu.reg
scripts/start-server.bat